[
  {
    "name": "Local-Cafe/localcafe-lite",
    "url": "https://github.com/Local-Cafe/localcafe-lite",
    "description": "A static site generator for local restaurants and cafes with no runtime js",
    "stars": 90,
    "forks": 8,
    "language": "CSS",
    "topics": [
      "cafe",
      "restaurants",
      "static-site-generator",
      "theme",
      "website"
    ],
    "license": "MIT License",
    "created_at": "2025-12-01T20:01:50Z",
    "updated_at": "2025-12-06T09:21:56Z",
    "owner": {
      "name": "Local-Cafe",
      "avatar_url": "https://avatars.githubusercontent.com/u/247235629?v=4"
    }
  },
  {
    "name": "pacholoamit/uptime-kuma-themes",
    "url": "https://github.com/pacholoamit/uptime-kuma-themes",
    "description": "A collection of Uptime Kuma Themes",
    "stars": 89,
    "forks": 3,
    "language": "CSS",
    "topics": [
      "monitoring",
      "uptime",
      "uptime-kuma"
    ],
    "license": "MIT License",
    "created_at": "2025-12-04T11:04:54Z",
    "updated_at": "2025-12-09T15:13:35Z",
    "owner": {
      "name": "pacholoamit",
      "avatar_url": "https://avatars.githubusercontent.com/u/69985528?v=4"
    }
  },
  {
    "name": "GoodrichDev/tinydc.net",
    "url": "https://github.com/GoodrichDev/tinydc.net",
    "description": "Interactive homelab rack visualizer powered by JSON, render hardware layouts, specs, and device info in a clean web UI.",
    "stars": 38,
    "forks": 5,
    "language": "CSS",
    "topics": [
      "dashboard",
      "datacenter",
      "docker",
      "docker-compose",
      "homelab",
      "homelab-automation",
      "homelab-setup",
      "javascript",
      "json",
      "network-tool",
      "rack",
      "rack-visualizer",
      "self-hosted",
      "server-inventory",
      "static-site",
      "sysadmin",
      "ui-tool",
      "visualization"
    ],
    "license": "No license",
    "created_at": "2025-11-27T08:30:50Z",
    "updated_at": "2025-12-02T10:04:28Z",
    "owner": {
      "name": "GoodrichDev",
      "avatar_url": "https://avatars.githubusercontent.com/u/147654894?v=4"
    }
  },
  {
    "name": "huuquockiet/GlassFox",
    "url": "https://github.com/huuquockiet/GlassFox",
    "description": "A glassy look for your Firefox!",
    "stars": 18,
    "forks": 0,
    "language": "CSS",
    "topics": [
      "css",
      "firefox-tweaks",
      "firefoxcss",
      "glass"
    ],
    "license": "No license",
    "created_at": "2025-12-01T07:18:33Z",
    "updated_at": "2025-12-06T18:54:04Z",
    "owner": {
      "name": "huuquockiet",
      "avatar_url": "https://avatars.githubusercontent.com/u/126334653?v=4"
    }
  },
  {
    "name": "boranfurkan/react-3d-button",
    "url": "https://github.com/boranfurkan/react-3d-button",
    "description": "React button component. React 3D button is a progress, social and share enabled, animated at 60fps, light weight, performant, production ready react UI button component. 🖥️ 📱 ",
    "stars": 17,
    "forks": 0,
    "language": "CSS",
    "topics": [],
    "license": "Other",
    "created_at": "2025-12-02T16:33:35Z",
    "updated_at": "2025-12-07T17:43:10Z",
    "owner": {
      "name": "boranfurkan",
      "avatar_url": "https://avatars.githubusercontent.com/u/96897046?v=4"
    }
  },
  {
    "name": "geohot/omarchy-boring-theme",
    "url": "https://github.com/geohot/omarchy-boring-theme",
    "description": "The most boring theme for omarchy",
    "stars": 15,
    "forks": 0,
    "language": "CSS",
    "topics": [],
    "license": "No license",
    "created_at": "2025-12-03T03:26:06Z",
    "updated_at": "2025-12-08T18:19:26Z",
    "owner": {
      "name": "geohot",
      "avatar_url": "https://avatars.githubusercontent.com/u/72895?v=4"
    }
  },
  {
    "name": "tznthou/muripo-hq",
    "url": "https://github.com/tznthou/muripo-hq",
    "description": "30 天 30 Repo 挑戰 — 2025/11/30 ~ 2025/12/30",
    "stars": 15,
    "forks": 0,
    "language": "CSS",
    "topics": [],
    "license": "MIT License",
    "created_at": "2025-11-29T15:52:33Z",
    "updated_at": "2025-12-04T16:09:57Z",
    "owner": {
      "name": "tznthou",
      "avatar_url": "https://avatars.githubusercontent.com/u/2958534?v=4"
    }
  },
  {
    "name": "InfoYaseer/Weather-App-Js",
    "url": "https://github.com/InfoYaseer/Weather-App-Js",
    "description": null,
    "stars": 14,
    "forks": 0,
    "language": "CSS",
    "topics": [],
    "license": "No license",
    "created_at": "2025-12-12T06:19:14Z",
    "updated_at": "2025-12-15T16:13:42Z",
    "owner": {
      "name": "InfoYaseer",
      "avatar_url": "https://avatars.githubusercontent.com/u/160985940?v=4"
    }
  },
  {
    "name": "scartoni/dotfiles",
    "url": "https://github.com/scartoni/dotfiles",
    "description": null,
    "stars": 10,
    "forks": 2,
    "language": "CSS",
    "topics": [],
    "license": "No license",
    "created_at": "2025-12-08T16:41:45Z",
    "updated_at": "2025-12-12T22:58:47Z",
    "owner": {
      "name": "scartoni",
      "avatar_url": "https://avatars.githubusercontent.com/u/98060105?v=4"
    }
  }
]