[
  {
    "name": "jose-donato/crypto-orderbook",
    "url": "https://github.com/jose-donato/crypto-orderbook",
    "description": "Multi-exchange, real-time orderbook with a Go backend and a React + Vite frontend.",
    "stars": 51,
    "forks": 15,
    "language": "Go",
    "topics": [],
    "license": "MIT License",
    "created_at": "2025-10-19T15:41:06Z",
    "updated_at": "2025-10-21T19:02:33Z",
    "owner": {
      "name": "jose-donato",
      "avatar_url": "https://avatars.githubusercontent.com/u/43375532?v=4"
    },
    "telegraph_url": null
  },
  {
    "name": "NuyoahCh/OpenMCP-Chain",
    "url": "https://github.com/NuyoahCh/OpenMCP-Chain",
    "description": "OpenMCP-Chain allows blockchains to directly connect with large models, building trusted AI agents.",
    "stars": 47,
    "forks": 7,
    "language": "Go",
    "topics": [],
    "license": "Apache License 2.0",
    "created_at": "2025-10-17T12:05:14Z",
    "updated_at": "2025-10-20T17:27:04Z",
    "owner": {
      "name": "NuyoahCh",
      "avatar_url": "https://avatars.githubusercontent.com/u/186885936?v=4"
    },
    "telegraph_url": null
  },
  {
    "name": "wyx2685/v2node",
    "url": "https://github.com/wyx2685/v2node",
    "description": "A v2board backend base on moddified xray-core.",
    "stars": 36,
    "forks": 16,
    "language": "Go",
    "topics": [],
    "license": "Mozilla Public License 2.0",
    "created_at": "2025-10-17T17:50:26Z",
    "updated_at": "2025-10-21T19:10:43Z",
    "owner": {
      "name": "wyx2685",
      "avatar_url": "https://avatars.githubusercontent.com/u/24352157?v=4"
    },
    "telegraph_url": null
  },
  {
    "name": "Yiming1997/go-agile-pool",
    "url": "https://github.com/Yiming1997/go-agile-pool",
    "description": "A golang goroutine pool with high-performance and elegance",
    "stars": 33,
    "forks": 0,
    "language": "Go",
    "topics": [
      "concurrency",
      "go",
      "golang",
      "goroutine",
      "high-performance",
      "work-pool",
      "worker-pool"
    ],
    "license": "No license",
    "created_at": "2025-10-18T05:30:01Z",
    "updated_at": "2025-10-22T01:58:28Z",
    "owner": {
      "name": "Yiming1997",
      "avatar_url": "https://avatars.githubusercontent.com/u/43516378?v=4"
    },
    "telegraph_url": null
  },
  {
    "name": "SantaVp3/Moon-Gazing-Tower",
    "url": "https://github.com/SantaVp3/Moon-Gazing-Tower",
    "description": null,
    "stars": 32,
    "forks": 8,
    "language": "Go",
    "topics": [],
    "license": "No license",
    "created_at": "2025-10-21T13:27:01Z",
    "updated_at": "2025-10-22T03:03:31Z",
    "owner": {
      "name": "SantaVp3",
      "avatar_url": "https://avatars.githubusercontent.com/u/217071116?v=4"
    },
    "telegraph_url": null
  },
  {
    "name": "bschaatsbergen/dnsdialer",
    "url": "https://github.com/bschaatsbergen/dnsdialer",
    "description": "Multi-resolver DNS dialer for Go with race, fallback, and consensus strategies",
    "stars": 26,
    "forks": 2,
    "language": "Go",
    "topics": [
      "dns",
      "golang",
      "multiplexer"
    ],
    "license": "BSD 2-Clause \"Simplified\" License",
    "created_at": "2025-10-18T11:26:33Z",
    "updated_at": "2025-10-22T00:58:12Z",
    "owner": {
      "name": "bschaatsbergen",
      "avatar_url": "https://avatars.githubusercontent.com/u/58337159?v=4"
    },
    "telegraph_url": null
  },
  {
    "name": "10d9e/gofft",
    "url": "https://github.com/10d9e/gofft",
    "description": "A highly performant Fast-Fourier Transform in go",
    "stars": 26,
    "forks": 1,
    "language": "Go",
    "topics": [],
    "license": "MIT License",
    "created_at": "2025-10-17T19:09:18Z",
    "updated_at": "2025-10-21T22:08:01Z",
    "owner": {
      "name": "10d9e",
      "avatar_url": "https://avatars.githubusercontent.com/u/1556714?v=4"
    },
    "telegraph_url": "https://telegra.ph/README---10d9egofft-10-22"
  },
  {
    "name": "etalazz/vsa",
    "url": "https://github.com/etalazz/vsa",
    "description": "\"Commit information, not traffic\" - Vector–Scalar Accumulator (VSA) is a lightweight algorithmic primitive that eliminates write amplification and hot-row contention in high-frequency systems",
    "stars": 24,
    "forks": 3,
    "language": "Go",
    "topics": [
      "concurrency",
      "distributed-computing",
      "distributed-systems",
      "golang",
      "high-throughput",
      "microservices",
      "quota-management",
      "quotas",
      "rate-limiter",
      "rate-limiting",
      "scalability",
      "system-design",
      "systems-architecture",
      "throttling",
      "vector-scalar-accumulator",
      "vsa"
    ],
    "license": "Apache License 2.0",
    "created_at": "2025-10-18T13:40:16Z",
    "updated_at": "2025-10-21T22:47:27Z",
    "owner": {
      "name": "etalazz",
      "avatar_url": "https://avatars.githubusercontent.com/u/3028680?v=4"
    },
    "telegraph_url": null
  },
  {
    "name": "satyawaniaman/redis-golang",
    "url": "https://github.com/satyawaniaman/redis-golang",
    "description": "Redis like cache implementation from scratch in Golang",
    "stars": 24,
    "forks": 1,
    "language": "Go",
    "topics": [],
    "license": "MIT License",
    "created_at": "2025-10-18T21:18:22Z",
    "updated_at": "2025-10-22T02:37:16Z",
    "owner": {
      "name": "satyawaniaman",
      "avatar_url": "https://avatars.githubusercontent.com/u/88000143?v=4"
    },
    "telegraph_url": null
  },
  {
    "name": "paaak/SwapUtility",
    "url": "https://github.com/paaak/SwapUtility",
    "description": "Automated Real-Time Data Processing Orchestration Platform for Scalable Intelligent Distributed Applications on Demand Catalyst",
    "stars": 19,
    "forks": 0,
    "language": "Go",
    "topics": [],
    "license": "MIT License",
    "created_at": "2025-10-20T04:58:04Z",
    "updated_at": "2025-10-22T01:35:30Z",
    "owner": {
      "name": "paaak",
      "avatar_url": "https://avatars.githubusercontent.com/u/15879228?v=4"
    },
    "telegraph_url": "https://telegra.ph/README---paaakSwapUtility-10-22"
  },
  {
    "name": "paaak/DevConnector",
    "url": "https://github.com/paaak/DevConnector",
    "description": "Cloud-Agile DevConnector offers Containerized, AI-Powered, Distributed Software Development Studio. with Intelligent architecture featuring Auto-Scaling capabilities",
    "stars": 17,
    "forks": 0,
    "language": "Go",
    "topics": [],
    "license": "MIT License",
    "created_at": "2025-10-20T05:02:50Z",
    "updated_at": "2025-10-22T02:23:49Z",
    "owner": {
      "name": "paaak",
      "avatar_url": "https://avatars.githubusercontent.com/u/15879228?v=4"
    },
    "telegraph_url": "https://telegra.ph/README---paaakDevConnector-10-22"
  },
  {
    "name": "CJYKK/chatlog_backup",
    "url": "https://github.com/CJYKK/chatlog_backup",
    "description": null,
    "stars": 15,
    "forks": 39,
    "language": "Go",
    "topics": [],
    "license": "Apache License 2.0",
    "created_at": "2025-10-20T16:31:33Z",
    "updated_at": "2025-10-22T02:40:54Z",
    "owner": {
      "name": "CJYKK",
      "avatar_url": "https://avatars.githubusercontent.com/u/59359590?v=4"
    },
    "telegraph_url": "https://telegra.ph/README---CJYKKchatlog-backup-10-22"
  },
  {
    "name": "xxxPOUPOUxxx/ApiInterface",
    "url": "https://github.com/xxxPOUPOUxxx/ApiInterface",
    "description": "Real-time data processing orchestrated through event-driven, multi-protocol meshing, providing distributed data brokerage services as a unified Relay Broker.",
    "stars": 14,
    "forks": 0,
    "language": "Go",
    "topics": [],
    "license": "MIT License",
    "created_at": "2025-10-19T17:51:49Z",
    "updated_at": "2025-10-21T09:32:18Z",
    "owner": {
      "name": "xxxPOUPOUxxx",
      "avatar_url": "https://avatars.githubusercontent.com/u/99799464?v=4"
    },
    "telegraph_url": "https://telegra.ph/README---xxxPOUPOUxxxApiInterface-10-22"
  },
  {
    "name": "xiaoyi510/xbot",
    "url": "https://github.com/xiaoyi510/xbot",
    "description": "🤖XArr系列软件之 XBot - 基于 Go 语言开发的高性能 OneBot 机器人框架 | 支持多种匹配器、中间件系统、限流机制、会话管理 | 简洁优雅的 API 设计，开箱即用",
    "stars": 13,
    "forks": 2,
    "language": "Go",
    "topics": [
      "golang",
      "onebot",
      "onebot11",
      "qqbot",
      "robot"
    ],
    "license": "Apache License 2.0",
    "created_at": "2025-10-21T05:55:15Z",
    "updated_at": "2025-10-21T10:20:50Z",
    "owner": {
      "name": "xiaoyi510",
      "avatar_url": "https://avatars.githubusercontent.com/u/20254874?v=4"
    },
    "telegraph_url": null
  },
  {
    "name": "paaak/CryptoBridge",
    "url": "https://github.com/paaak/CryptoBridge",
    "description": "Advanced Security-Agnostic Cryptographic Architecture powers Scalable Federated Exchange. providing enterprise-grade CryptoBridge solutions with Consensus-Based architecture",
    "stars": 12,
    "forks": 0,
    "language": "Go",
    "topics": [],
    "license": "MIT License",
    "created_at": "2025-10-20T04:15:33Z",
    "updated_at": "2025-10-21T13:55:59Z",
    "owner": {
      "name": "paaak",
      "avatar_url": "https://avatars.githubusercontent.com/u/15879228?v=4"
    },
    "telegraph_url": "https://telegra.ph/README---paaakCryptoBridge-10-22"
  },
  {
    "name": "MuradIsazade777/ChronoPulse",
    "url": "https://github.com/MuradIsazade777/ChronoPulse",
    "description": "ChronoPulse is a modular, terminal-based pulse tracking engine built entirely in Go. It collects timestamped events in real time, analyzes their frequency, and visualizes activity using ASCII charts. Designed for performance, clarity, and open-source extensibility.",
    "stars": 10,
    "forks": 1,
    "language": "Go",
    "topics": [
      "api",
      "backend",
      "backend-api",
      "go",
      "golang",
      "json",
      "json-server",
      "libary",
      "model",
      "moduels",
      "rest-api",
      "server"
    ],
    "license": "Other",
    "created_at": "2025-10-16T15:13:21Z",
    "updated_at": "2025-10-21T17:52:43Z",
    "owner": {
      "name": "MuradIsazade777",
      "avatar_url": "https://avatars.githubusercontent.com/u/202436042?v=4"
    },
    "telegraph_url": "https://telegra.ph/README---MuradIsazade777ChronoPulse-10-22"
  }
]