[
  {
    "name": "babycommando/zuse",
    "url": "https://github.com/babycommando/zuse",
    "description": "ZUSE is an irc client for the terminal made in Go with Bubbletea",
    "stars": 216,
    "forks": 7,
    "language": "Go",
    "topics": [],
    "license": "Apache License 2.0",
    "created_at": "2025-07-27T22:12:35Z",
    "updated_at": "2025-07-31T00:38:53Z",
    "owner": {
      "name": "babycommando",
      "avatar_url": "https://avatars.githubusercontent.com/u/71618056?v=4"
    },
    "telegraph_url": null
  },
  {
    "name": "0x4D31/finch",
    "url": "https://github.com/0x4D31/finch",
    "description": "Fingerprint-aware TLS reverse proxy. Use Finch to outsmart bad traffic—collect client fingerprints (JA3, JA4 +QUIC, JA4H, HTTP/2) and act on them: block, reroute, tarpit, or deceive in real time.",
    "stars": 116,
    "forks": 7,
    "language": "Go",
    "topics": [
      "deception",
      "fingerprint",
      "fingerprinting",
      "go",
      "honeypot",
      "ja3",
      "ja4",
      "reverse-proxy",
      "security",
      "security-tools"
    ],
    "license": "Apache License 2.0",
    "created_at": "2025-07-27T18:16:58Z",
    "updated_at": "2025-07-30T23:09:18Z",
    "owner": {
      "name": "0x4D31",
      "avatar_url": "https://avatars.githubusercontent.com/u/11577776?v=4"
    },
    "telegraph_url": null
  },
  {
    "name": "MuhammadWaseem29/BackupFinder",
    "url": "https://github.com/MuhammadWaseem29/BackupFinder",
    "description": "BackupFinder discovers backup files on web servers by generating intelligent patterns.",
    "stars": 75,
    "forks": 16,
    "language": "Go",
    "topics": [
      "backupfinder",
      "bug",
      "bugbounty",
      "bugcrowd",
      "ffuf",
      "hackerone",
      "open-source",
      "wordlist-generator",
      "yeswehack"
    ],
    "license": "Other",
    "created_at": "2025-07-25T13:10:09Z",
    "updated_at": "2025-07-31T02:24:29Z",
    "owner": {
      "name": "MuhammadWaseem29",
      "avatar_url": "https://avatars.githubusercontent.com/u/161931698?v=4"
    },
    "telegraph_url": null
  },
  {
    "name": "checkly-go/checkly",
    "url": "https://github.com/checkly-go/checkly",
    "description": "packages, cli and api for website analysis ",
    "stars": 39,
    "forks": 0,
    "language": "Go",
    "topics": [
      "backend",
      "backend-api",
      "docker",
      "gin",
      "golang",
      "golang-application",
      "golang-library",
      "golang-package",
      "hosting",
      "mongodb",
      "server"
    ],
    "license": "No license",
    "created_at": "2025-07-26T18:52:44Z",
    "updated_at": "2025-07-30T20:49:05Z",
    "owner": {
      "name": "checkly-go",
      "avatar_url": "https://avatars.githubusercontent.com/u/223197788?v=4"
    },
    "telegraph_url": null
  },
  {
    "name": "yurikdotdev/covfefescript",
    "url": "https://github.com/yurikdotdev/covfefescript",
    "description": "A Trumpian-syntax Turing-complete interpreted language. (Boot.dev Hackathon)",
    "stars": 30,
    "forks": 0,
    "language": "Go",
    "topics": [
      "golang",
      "hackathon",
      "interpreter",
      "meme",
      "pratt-parser",
      "repl",
      "toy-language",
      "tree-walk-interpreter"
    ],
    "license": "MIT License",
    "created_at": "2025-07-26T10:23:24Z",
    "updated_at": "2025-07-29T22:21:43Z",
    "owner": {
      "name": "yurikdotdev",
      "avatar_url": "https://avatars.githubusercontent.com/u/172495341?v=4"
    },
    "telegraph_url": null
  },
  {
    "name": "maniac-en/req",
    "url": "https://github.com/maniac-en/req",
    "description": "Req - Test APIs with Terminal Velocity",
    "stars": 29,
    "forks": 0,
    "language": "Go",
    "topics": [
      "api",
      "bubbletea",
      "cli",
      "go",
      "terminal",
      "testing",
      "tui"
    ],
    "license": "Other",
    "created_at": "2025-07-25T15:23:50Z",
    "updated_at": "2025-07-30T10:10:10Z",
    "owner": {
      "name": "maniac-en",
      "avatar_url": "https://avatars.githubusercontent.com/u/45049766?v=4"
    },
    "telegraph_url": null
  },
  {
    "name": "Vedjw/DonkeyType",
    "url": "https://github.com/Vedjw/DonkeyType",
    "description": null,
    "stars": 29,
    "forks": 0,
    "language": "Go",
    "topics": [],
    "license": "No license",
    "created_at": "2025-07-25T16:16:09Z",
    "updated_at": "2025-07-29T22:39:08Z",
    "owner": {
      "name": "Vedjw",
      "avatar_url": "https://avatars.githubusercontent.com/u/148562130?v=4"
    },
    "telegraph_url": null
  },
  {
    "name": "sriniously/go-boilerplate",
    "url": "https://github.com/sriniously/go-boilerplate",
    "description": "A production grade Go boilerplate",
    "stars": 26,
    "forks": 2,
    "language": "Go",
    "topics": [],
    "license": "MIT License",
    "created_at": "2025-07-29T16:25:43Z",
    "updated_at": "2025-07-31T03:23:52Z",
    "owner": {
      "name": "sriniously",
      "avatar_url": "https://avatars.githubusercontent.com/u/47584722?v=4"
    },
    "telegraph_url": null
  },
  {
    "name": "shumy26/Sir-Lints-a-Lot",
    "url": "https://github.com/shumy26/Sir-Lints-a-Lot",
    "description": null,
    "stars": 23,
    "forks": 0,
    "language": "Go",
    "topics": [],
    "license": "No license",
    "created_at": "2025-07-25T15:45:48Z",
    "updated_at": "2025-07-29T22:21:21Z",
    "owner": {
      "name": "shumy26",
      "avatar_url": "https://avatars.githubusercontent.com/u/134865899?v=4"
    },
    "telegraph_url": null
  },
  {
    "name": "redbco/redb-open",
    "url": "https://github.com/redbco/redb-open",
    "description": "Distributed data mesh for real-time access, migration, and replication across diverse databases — built for AI, security, and scale.",
    "stars": 23,
    "forks": 0,
    "language": "Go",
    "topics": [
      "ai-infrastructure",
      "compliance",
      "data-mesh",
      "data-migration",
      "data-obfuscation",
      "data-portability",
      "data-replication",
      "distributed-systems",
      "golang",
      "open-source",
      "policy-driven",
      "schema-versioning"
    ],
    "license": "GNU Affero General Public License v3.0",
    "created_at": "2025-07-26T10:14:21Z",
    "updated_at": "2025-07-31T01:01:34Z",
    "owner": {
      "name": "redbco",
      "avatar_url": "https://avatars.githubusercontent.com/u/170182025?v=4"
    },
    "telegraph_url": null
  },
  {
    "name": "zhoudm1743/go-cache",
    "url": "https://github.com/zhoudm1743/go-cache",
    "description": "GO语言缓存库，支持内存、文件、Redis三种实现方式，提供统一接口和丰富的数据结构操作。",
    "stars": 22,
    "forks": 0,
    "language": "Go",
    "topics": [
      "cache",
      "file",
      "golang",
      "memory",
      "redis"
    ],
    "license": "MIT License",
    "created_at": "2025-07-25T13:47:44Z",
    "updated_at": "2025-07-27T07:17:08Z",
    "owner": {
      "name": "zhoudm1743",
      "avatar_url": "https://avatars.githubusercontent.com/u/202275785?v=4"
    },
    "telegraph_url": null
  },
  {
    "name": "FeliciaFredlund/trackinstall",
    "url": "https://github.com/FeliciaFredlund/trackinstall",
    "description": "A CLI to track manually installed programs/apps and their dependencies.",
    "stars": 19,
    "forks": 0,
    "language": "Go",
    "topics": [],
    "license": "No license",
    "created_at": "2025-07-25T16:19:42Z",
    "updated_at": "2025-07-29T18:54:13Z",
    "owner": {
      "name": "FeliciaFredlund",
      "avatar_url": "https://avatars.githubusercontent.com/u/103130280?v=4"
    },
    "telegraph_url": null
  },
  {
    "name": "Asfolny/geaves",
    "url": "https://github.com/Asfolny/geaves",
    "description": null,
    "stars": 19,
    "forks": 0,
    "language": "Go",
    "topics": [],
    "license": "MIT License",
    "created_at": "2025-07-25T20:56:30Z",
    "updated_at": "2025-07-28T15:52:49Z",
    "owner": {
      "name": "Asfolny",
      "avatar_url": "https://avatars.githubusercontent.com/u/19804492?v=4"
    },
    "telegraph_url": null
  },
  {
    "name": "FT1006/devesis",
    "url": "https://github.com/FT1006/devesis",
    "description": "A CLI survival horror game inspired by Nemesis and Boot.dev where hackathon developers escape Tutorial Hell",
    "stars": 18,
    "forks": 0,
    "language": "Go",
    "topics": [],
    "license": "MIT License",
    "created_at": "2025-07-25T21:10:20Z",
    "updated_at": "2025-07-29T20:50:24Z",
    "owner": {
      "name": "FT1006",
      "avatar_url": "https://avatars.githubusercontent.com/u/111700930?v=4"
    },
    "telegraph_url": null
  },
  {
    "name": "kawilkinson/gocade",
    "url": "https://github.com/kawilkinson/gocade",
    "description": null,
    "stars": 18,
    "forks": 0,
    "language": "Go",
    "topics": [],
    "license": "MIT License",
    "created_at": "2025-07-25T16:05:09Z",
    "updated_at": "2025-07-30T13:03:08Z",
    "owner": {
      "name": "kawilkinson",
      "avatar_url": "https://avatars.githubusercontent.com/u/178110662?v=4"
    },
    "telegraph_url": null
  },
  {
    "name": "nalgeon/azor",
    "url": "https://github.com/nalgeon/azor",
    "description": "Promises and async/await in Go",
    "stars": 18,
    "forks": 0,
    "language": "Go",
    "topics": [
      "async",
      "await",
      "promise"
    ],
    "license": "MIT License",
    "created_at": "2025-07-27T14:58:18Z",
    "updated_at": "2025-07-29T15:54:53Z",
    "owner": {
      "name": "nalgeon",
      "avatar_url": "https://avatars.githubusercontent.com/u/2946182?v=4"
    },
    "telegraph_url": null
  },
  {
    "name": "matteo-grella/dwarfreflect",
    "url": "https://github.com/matteo-grella/dwarfreflect",
    "description": "Enhanced Go reflection using DWARF debug information to extract function parameter names",
    "stars": 17,
    "forks": 0,
    "language": "Go",
    "topics": [],
    "license": "MIT License",
    "created_at": "2025-07-29T09:51:27Z",
    "updated_at": "2025-07-31T02:44:59Z",
    "owner": {
      "name": "matteo-grella",
      "avatar_url": "https://avatars.githubusercontent.com/u/5662657?v=4"
    },
    "telegraph_url": null
  },
  {
    "name": "bdbrwr/api-replay",
    "url": "https://github.com/bdbrwr/api-replay",
    "description": null,
    "stars": 16,
    "forks": 0,
    "language": "Go",
    "topics": [],
    "license": "No license",
    "created_at": "2025-07-25T20:48:35Z",
    "updated_at": "2025-07-30T13:14:33Z",
    "owner": {
      "name": "bdbrwr",
      "avatar_url": "https://avatars.githubusercontent.com/u/82840731?v=4"
    },
    "telegraph_url": null
  },
  {
    "name": "Ceinl/Go-dashboard",
    "url": "https://github.com/Ceinl/Go-dashboard",
    "description": null,
    "stars": 16,
    "forks": 0,
    "language": "Go",
    "topics": [],
    "license": "MIT License",
    "created_at": "2025-07-25T20:03:30Z",
    "updated_at": "2025-07-28T16:33:05Z",
    "owner": {
      "name": "Ceinl",
      "avatar_url": "https://avatars.githubusercontent.com/u/73730760?v=4"
    },
    "telegraph_url": null
  },
  {
    "name": "chee-zer/sd-bro",
    "url": "https://github.com/chee-zer/sd-bro",
    "description": "project for the Boot Dev 2025 hackathon",
    "stars": 15,
    "forks": 0,
    "language": "Go",
    "topics": [],
    "license": "No license",
    "created_at": "2025-07-26T06:26:39Z",
    "updated_at": "2025-07-29T00:17:32Z",
    "owner": {
      "name": "chee-zer",
      "avatar_url": "https://avatars.githubusercontent.com/u/141304932?v=4"
    },
    "telegraph_url": null
  },
  {
    "name": "huaimeng666/gofinger",
    "url": "https://github.com/huaimeng666/gofinger",
    "description": "GoFinger是一款专为红队攻防和企业资产管理设计的下一代指纹发现、指纹识别工具。基于 Go 语言开发，它不仅继承了传统指纹工具的识别能力，更在**性能、可扩展性和输出质量**上进行了深度优化。  它旨在帮助安全工程师和渗透测试人员快速、精准地识别网络资产指纹，并以美观、易读的格式呈现结果。工具原生支持本地指纹库与 Fofa、Quake、Hunter 等主流API联动，并集成了 Chainreactors Fingers、Goby、Ehole、Wappalyzer 等多种知名指纹库，是现代网络空间测绘和资产管理不可或缺的瑞士军刀。",
    "stars": 15,
    "forks": 2,
    "language": "Go",
    "topics": [],
    "license": "MIT License",
    "created_at": "2025-07-25T05:00:53Z",
    "updated_at": "2025-07-31T02:37:03Z",
    "owner": {
      "name": "huaimeng666",
      "avatar_url": "https://avatars.githubusercontent.com/u/76671878?v=4"
    },
    "telegraph_url": null
  },
  {
    "name": "caidaoli/kiro2api",
    "url": "https://github.com/caidaoli/kiro2api",
    "description": null,
    "stars": 15,
    "forks": 1,
    "language": "Go",
    "topics": [],
    "license": "No license",
    "created_at": "2025-07-25T06:53:44Z",
    "updated_at": "2025-07-30T15:31:43Z",
    "owner": {
      "name": "caidaoli",
      "avatar_url": "https://avatars.githubusercontent.com/u/3807815?v=4"
    },
    "telegraph_url": null
  },
  {
    "name": "haley-marie/growlog",
    "url": "https://github.com/haley-marie/growlog",
    "description": null,
    "stars": 14,
    "forks": 0,
    "language": "Go",
    "topics": [],
    "license": "No license",
    "created_at": "2025-07-26T15:34:26Z",
    "updated_at": "2025-07-28T16:37:32Z",
    "owner": {
      "name": "haley-marie",
      "avatar_url": "https://avatars.githubusercontent.com/u/165605530?v=4"
    },
    "telegraph_url": null
  },
  {
    "name": "sainikmandal/diary-in-terminal",
    "url": "https://github.com/sainikmandal/diary-in-terminal",
    "description": null,
    "stars": 14,
    "forks": 0,
    "language": "Go",
    "topics": [],
    "license": "No license",
    "created_at": "2025-07-26T10:59:41Z",
    "updated_at": "2025-07-29T02:02:02Z",
    "owner": {
      "name": "sainikmandal",
      "avatar_url": "https://avatars.githubusercontent.com/u/68194201?v=4"
    },
    "telegraph_url": null
  },
  {
    "name": "sammwyy/yfs",
    "url": "https://github.com/sammwyy/yfs",
    "description": "A Vertical file system implementation in Go that stores everything in three files: index, bitmap (block tracking), and block storage.",
    "stars": 13,
    "forks": 1,
    "language": "Go",
    "topics": [],
    "license": "MIT License",
    "created_at": "2025-07-27T23:07:41Z",
    "updated_at": "2025-07-30T05:33:21Z",
    "owner": {
      "name": "sammwyy",
      "avatar_url": "https://avatars.githubusercontent.com/u/44925968?v=4"
    },
    "telegraph_url": null
  },
  {
    "name": "nunseik/forma",
    "url": "https://github.com/nunseik/forma",
    "description": null,
    "stars": 11,
    "forks": 0,
    "language": "Go",
    "topics": [],
    "license": "Other",
    "created_at": "2025-07-25T21:12:06Z",
    "updated_at": "2025-07-29T07:06:58Z",
    "owner": {
      "name": "nunseik",
      "avatar_url": "https://avatars.githubusercontent.com/u/63461851?v=4"
    },
    "telegraph_url": null
  },
  {
    "name": "hackclub/arker",
    "url": "https://github.com/hackclub/arker",
    "description": "A lil' archive tool for saving public webpages, git repos, and YouTube videos",
    "stars": 11,
    "forks": 0,
    "language": "Go",
    "topics": [],
    "license": "MIT License",
    "created_at": "2025-07-25T14:25:44Z",
    "updated_at": "2025-07-30T18:44:56Z",
    "owner": {
      "name": "hackclub",
      "avatar_url": "https://avatars.githubusercontent.com/u/5633654?v=4"
    },
    "telegraph_url": null
  },
  {
    "name": "mattn/url-shortener",
    "url": "https://github.com/mattn/url-shortener",
    "description": "A simple and efficient URL shortening service written in Go.",
    "stars": 10,
    "forks": 1,
    "language": "Go",
    "topics": [
      "url-shortener"
    ],
    "license": "No license",
    "created_at": "2025-07-25T06:29:24Z",
    "updated_at": "2025-07-29T09:48:11Z",
    "owner": {
      "name": "mattn",
      "avatar_url": "https://avatars.githubusercontent.com/u/10111?v=4"
    },
    "telegraph_url": null
  },
  {
    "name": "KaoriEl/json2any",
    "url": "https://github.com/KaoriEl/json2any",
    "description": "A CLI tool for converting between JSON and Excel (.xlsx), CSV, and TXT formats with support for theming, data type formatting, parallel processing, and bidirectional conversion.",
    "stars": 10,
    "forks": 0,
    "language": "Go",
    "topics": [],
    "license": "No license",
    "created_at": "2025-07-25T06:01:33Z",
    "updated_at": "2025-07-30T05:17:26Z",
    "owner": {
      "name": "KaoriEl",
      "avatar_url": "https://avatars.githubusercontent.com/u/55589981?v=4"
    },
    "telegraph_url": null
  },
  {
    "name": "hicugi/bootdev-hackathon-07-2025",
    "url": "https://github.com/hicugi/bootdev-hackathon-07-2025",
    "description": "Watch media by network across multiple devices",
    "stars": 10,
    "forks": 0,
    "language": "Go",
    "topics": [],
    "license": "MIT License",
    "created_at": "2025-07-26T08:36:19Z",
    "updated_at": "2025-07-30T03:32:52Z",
    "owner": {
      "name": "hicugi",
      "avatar_url": "https://avatars.githubusercontent.com/u/16819882?v=4"
    },
    "telegraph_url": null
  }
]