[
  {
    "name": "markrai/whatsthat",
    "url": "https://github.com/markrai/whatsthat",
    "description": "a brutally honest whatsapp web analyzer",
    "stars": 175,
    "forks": 7,
    "language": "JavaScript",
    "topics": [],
    "license": "MIT License",
    "created_at": "2025-10-13T16:15:15Z",
    "updated_at": "2025-10-16T23:55:38Z",
    "owner": {
      "name": "markrai",
      "avatar_url": "https://avatars.githubusercontent.com/u/28987673?v=4"
    },
    "telegraph_url": null
  },
  {
    "name": "tublydownloader/Firefox-YouTube-Downloader",
    "url": "https://github.com/tublydownloader/Firefox-YouTube-Downloader",
    "description": "Firefox add-on to download YouTube videos and Shorts, and convert to MP3 in one click.",
    "stars": 88,
    "forks": 1,
    "language": "JavaScript",
    "topics": [
      "browser-extension",
      "downloader",
      "downloader-for-youtube",
      "firefox-addon",
      "firefox-extension",
      "firefox-webextension",
      "video",
      "youtube",
      "youtube-4k-downloader",
      "youtube-dl",
      "youtube-downloader",
      "youtube-mp3",
      "youtube-mp3-converter",
      "youtube-mp3-downloader",
      "youtube-shorts-download",
      "youtube-video",
      "youtube-video-download"
    ],
    "license": "No license",
    "created_at": "2025-10-15T01:30:11Z",
    "updated_at": "2025-10-17T02:40:46Z",
    "owner": {
      "name": "tublydownloader",
      "avatar_url": "https://avatars.githubusercontent.com/u/196207974?v=4"
    },
    "telegraph_url": null
  },
  {
    "name": "alchaincyf/huasheng_editor",
    "url": "https://github.com/alchaincyf/huasheng_editor",
    "description": "花生公众号排版器",
    "stars": 78,
    "forks": 17,
    "language": "JavaScript",
    "topics": [],
    "license": "MIT License",
    "created_at": "2025-10-13T15:10:47Z",
    "updated_at": "2025-10-17T02:22:24Z",
    "owner": {
      "name": "alchaincyf",
      "avatar_url": "https://avatars.githubusercontent.com/u/127714341?v=4"
    },
    "telegraph_url": null
  },
  {
    "name": "RemotePinee/AudioVisual",
    "url": "https://github.com/RemotePinee/AudioVisual",
    "description": "解锁所有国内媒体流的钥匙",
    "stars": 72,
    "forks": 11,
    "language": "JavaScript",
    "topics": [],
    "license": "No license",
    "created_at": "2025-10-13T15:42:42Z",
    "updated_at": "2025-10-17T02:42:09Z",
    "owner": {
      "name": "RemotePinee",
      "avatar_url": "https://avatars.githubusercontent.com/u/76951454?v=4"
    },
    "telegraph_url": null
  },
  {
    "name": "SpicyMarinara/rpg-companion-sillytavern",
    "url": "https://github.com/SpicyMarinara/rpg-companion-sillytavern",
    "description": "RPG Companion extension for SillyTavern - Track characters, quests, inventory, and game state with AI-generated content",
    "stars": 48,
    "forks": 4,
    "language": "JavaScript",
    "topics": [],
    "license": "Other",
    "created_at": "2025-10-13T22:09:16Z",
    "updated_at": "2025-10-16T22:15:34Z",
    "owner": {
      "name": "SpicyMarinara",
      "avatar_url": "https://avatars.githubusercontent.com/u/45567659?v=4"
    },
    "telegraph_url": null
  },
  {
    "name": "code3-dev/doh-proxy-worker",
    "url": "https://github.com/code3-dev/doh-proxy-worker",
    "description": "High-performance Cloudflare Worker for proxying DNS-over-HTTPS (DoH) requests with multi-provider support, load balancing, caching, and failover.",
    "stars": 42,
    "forks": 11,
    "language": "JavaScript",
    "topics": [],
    "license": "MIT License",
    "created_at": "2025-10-12T23:12:03Z",
    "updated_at": "2025-10-16T23:08:12Z",
    "owner": {
      "name": "code3-dev",
      "avatar_url": "https://avatars.githubusercontent.com/u/158034265?v=4"
    },
    "telegraph_url": null
  },
  {
    "name": "DFin/palaeograph",
    "url": "https://github.com/DFin/palaeograph",
    "description": "Paleograph is a browser-based 3D viewer built for archaeologists who need to explore tabular measurement datasets.",
    "stars": 37,
    "forks": 4,
    "language": "JavaScript",
    "topics": [],
    "license": "MIT License",
    "created_at": "2025-10-11T14:12:46Z",
    "updated_at": "2025-10-17T01:25:20Z",
    "owner": {
      "name": "DFin",
      "avatar_url": "https://avatars.githubusercontent.com/u/6152468?v=4"
    },
    "telegraph_url": null
  },
  {
    "name": "NiffirgkcaJ/all-in-one-clipboard",
    "url": "https://github.com/NiffirgkcaJ/all-in-one-clipboard",
    "description": "A feature-rich clipboard manager for GNOME Shell that integrates clipboard history, an emoji picker with skin-tone support, GIF search, and extensive kaomoji/symbol libraries into a single, unified panel.",
    "stars": 33,
    "forks": 1,
    "language": "JavaScript",
    "topics": [],
    "license": "GNU General Public License v3.0",
    "created_at": "2025-10-12T08:29:50Z",
    "updated_at": "2025-10-16T20:18:37Z",
    "owner": {
      "name": "NiffirgkcaJ",
      "avatar_url": "https://avatars.githubusercontent.com/u/115857102?v=4"
    },
    "telegraph_url": null
  },
  {
    "name": "Willepille10aaa/bnb-fourmeme-bundler-copytrade-bot",
    "url": "https://github.com/Willepille10aaa/bnb-fourmeme-bundler-copytrade-bot",
    "description": "About Four.Meme BNB Trading Bot. Sniper Bot, Volume Bot, Bundler Bot. Contact for fourmeme trading bot",
    "stars": 23,
    "forks": 0,
    "language": "JavaScript",
    "topics": [
      "bnb",
      "bsc",
      "bundler",
      "four",
      "fourmeme",
      "sniper",
      "trading"
    ],
    "license": "No license",
    "created_at": "2025-10-11T21:51:08Z",
    "updated_at": "2025-10-16T22:44:09Z",
    "owner": {
      "name": "Willepille10aaa",
      "avatar_url": "https://avatars.githubusercontent.com/u/237427513?v=4"
    },
    "telegraph_url": null
  },
  {
    "name": "Novus-Tech-LLC/BSC-Mempool-Frontrun",
    "url": "https://github.com/Novus-Tech-LLC/BSC-Mempool-Frontrun",
    "description": "Multi-chain mempool trading bot with sniper, frontrun, backrun, and sandwich modules. Works across BSC, Ethereum, Avalanche, Polygon, and more.",
    "stars": 22,
    "forks": 11,
    "language": "JavaScript",
    "topics": [],
    "license": "No license",
    "created_at": "2025-10-14T13:39:19Z",
    "updated_at": "2025-10-15T21:55:33Z",
    "owner": {
      "name": "Novus-Tech-LLC",
      "avatar_url": "https://avatars.githubusercontent.com/u/237565620?v=4"
    },
    "telegraph_url": null
  },
  {
    "name": "b0b0b0b0b0b0b0b0b0b0b0b0b0b0b0b0/modrinth-proxy",
    "url": "https://github.com/b0b0b0b0b0b0b0b0b0b0b0b0b0b0b0b0/modrinth-proxy",
    "description": null,
    "stars": 22,
    "forks": 1,
    "language": "JavaScript",
    "topics": [],
    "license": "No license",
    "created_at": "2025-10-12T17:03:46Z",
    "updated_at": "2025-10-17T02:53:40Z",
    "owner": {
      "name": "b0b0b0b0b0b0b0b0b0b0b0b0b0b0b0b0",
      "avatar_url": "https://avatars.githubusercontent.com/u/119269640?v=4"
    },
    "telegraph_url": null
  },
  {
    "name": "ShengWang1017/Automatic-reset",
    "url": "https://github.com/ShengWang1017/Automatic-reset",
    "description": null,
    "stars": 20,
    "forks": 3,
    "language": "JavaScript",
    "topics": [],
    "license": "MIT License",
    "created_at": "2025-10-11T10:26:55Z",
    "updated_at": "2025-10-16T15:07:31Z",
    "owner": {
      "name": "ShengWang1017",
      "avatar_url": "https://avatars.githubusercontent.com/u/127858020?v=4"
    },
    "telegraph_url": null
  },
  {
    "name": "mrtian2016/wireguard-config-generator",
    "url": "https://github.com/mrtian2016/wireguard-config-generator",
    "description": "WireGuard client config generator | WireGuard 客户端配置生成工具",
    "stars": 19,
    "forks": 4,
    "language": "JavaScript",
    "topics": [
      "react",
      "rust",
      "tauri",
      "wireguard",
      "wireguard-config"
    ],
    "license": "No license",
    "created_at": "2025-10-12T11:21:48Z",
    "updated_at": "2025-10-17T02:20:58Z",
    "owner": {
      "name": "mrtian2016",
      "avatar_url": "https://avatars.githubusercontent.com/u/20147943?v=4"
    },
    "telegraph_url": null
  },
  {
    "name": "empowerd-cms/nyno",
    "url": "https://github.com/empowerd-cms/nyno",
    "description": "Create and Run Linux Workflows without Limits. Short for \"nine\" / \"yaml\" / \"no-code\" / \"automation\". ",
    "stars": 19,
    "forks": 0,
    "language": "JavaScript",
    "topics": [],
    "license": "Apache License 2.0",
    "created_at": "2025-10-12T17:41:16Z",
    "updated_at": "2025-10-16T13:21:40Z",
    "owner": {
      "name": "empowerd-cms",
      "avatar_url": "https://avatars.githubusercontent.com/u/234256210?v=4"
    },
    "telegraph_url": null
  },
  {
    "name": "KleinerSource/droid2api-multi-key-support",
    "url": "https://github.com/KleinerSource/droid2api-multi-key-support",
    "description": null,
    "stars": 18,
    "forks": 6,
    "language": "JavaScript",
    "topics": [],
    "license": "No license",
    "created_at": "2025-10-13T07:48:04Z",
    "updated_at": "2025-10-16T08:00:43Z",
    "owner": {
      "name": "KleinerSource",
      "avatar_url": "https://avatars.githubusercontent.com/u/920875?v=4"
    },
    "telegraph_url": null
  },
  {
    "name": "cat9999aaa/zhangfei-eat-douya",
    "url": "https://github.com/cat9999aaa/zhangfei-eat-douya",
    "description": "张飞吃豆芽，越吃越有",
    "stars": 17,
    "forks": 9,
    "language": "JavaScript",
    "topics": [],
    "license": "No license",
    "created_at": "2025-10-15T14:07:31Z",
    "updated_at": "2025-10-17T02:40:33Z",
    "owner": {
      "name": "cat9999aaa",
      "avatar_url": "https://avatars.githubusercontent.com/u/142902882?v=4"
    },
    "telegraph_url": null
  },
  {
    "name": "smyth64/ibkr-pnl-visualizer",
    "url": "https://github.com/smyth64/ibkr-pnl-visualizer",
    "description": null,
    "stars": 17,
    "forks": 0,
    "language": "JavaScript",
    "topics": [],
    "license": "No license",
    "created_at": "2025-10-15T02:20:38Z",
    "updated_at": "2025-10-16T19:31:08Z",
    "owner": {
      "name": "smyth64",
      "avatar_url": "https://avatars.githubusercontent.com/u/3246782?v=4"
    },
    "telegraph_url": null
  },
  {
    "name": "2102ankit/react-datatable",
    "url": "https://github.com/2102ankit/react-datatable",
    "description": null,
    "stars": 16,
    "forks": 0,
    "language": "JavaScript",
    "topics": [],
    "license": "No license",
    "created_at": "2025-10-12T17:37:39Z",
    "updated_at": "2025-10-14T17:23:49Z",
    "owner": {
      "name": "2102ankit",
      "avatar_url": "https://avatars.githubusercontent.com/u/105378102?v=4"
    },
    "telegraph_url": null
  },
  {
    "name": "dmkskd/sql-shader",
    "url": "https://github.com/dmkskd/sql-shader",
    "description": null,
    "stars": 16,
    "forks": 1,
    "language": "JavaScript",
    "topics": [],
    "license": "Other",
    "created_at": "2025-10-13T13:54:36Z",
    "updated_at": "2025-10-16T16:41:48Z",
    "owner": {
      "name": "dmkskd",
      "avatar_url": "https://avatars.githubusercontent.com/u/46271281?v=4"
    },
    "telegraph_url": null
  },
  {
    "name": "MatiasDesuu/ThinkDashboard",
    "url": "https://github.com/MatiasDesuu/ThinkDashboard",
    "description": "A lightweight, self-hosted bookmark dashboard with keyboard shortcuts.",
    "stars": 16,
    "forks": 0,
    "language": "JavaScript",
    "topics": [
      "bookmarks",
      "dashboard",
      "golang",
      "minimalist",
      "selfhost",
      "selfhosted",
      "terminal",
      "tty"
    ],
    "license": "MIT License",
    "created_at": "2025-10-11T12:42:20Z",
    "updated_at": "2025-10-16T21:10:00Z",
    "owner": {
      "name": "MatiasDesuu",
      "avatar_url": "https://avatars.githubusercontent.com/u/17015798?v=4"
    },
    "telegraph_url": null
  },
  {
    "name": "SunXin121/bing_wallpaper",
    "url": "https://github.com/SunXin121/bing_wallpaper",
    "description": "自建 bing 随机壁纸 API",
    "stars": 16,
    "forks": 8,
    "language": "JavaScript",
    "topics": [],
    "license": "Apache License 2.0",
    "created_at": "2025-10-11T06:37:03Z",
    "updated_at": "2025-10-15T13:48:44Z",
    "owner": {
      "name": "SunXin121",
      "avatar_url": "https://avatars.githubusercontent.com/u/111034439?v=4"
    },
    "telegraph_url": null
  },
  {
    "name": "theletterf/vale-mcp-server",
    "url": "https://github.com/theletterf/vale-mcp-server",
    "description": "MCP server for the Vale linter",
    "stars": 15,
    "forks": 2,
    "language": "JavaScript",
    "topics": [
      "linter",
      "mcp",
      "mcp-server",
      "vale"
    ],
    "license": "MIT License",
    "created_at": "2025-10-12T15:29:24Z",
    "updated_at": "2025-10-16T16:44:45Z",
    "owner": {
      "name": "theletterf",
      "avatar_url": "https://avatars.githubusercontent.com/u/1773616?v=4"
    },
    "telegraph_url": null
  },
  {
    "name": "phpcalm/exceed",
    "url": "https://github.com/phpcalm/exceed",
    "description": "一个功能强大的浏览器扩展程序，专门用于检测Web系统中的权限越权漏洞，适用于Web渗透测试。",
    "stars": 15,
    "forks": 0,
    "language": "JavaScript",
    "topics": [],
    "license": "No license",
    "created_at": "2025-10-11T01:21:52Z",
    "updated_at": "2025-10-16T03:06:52Z",
    "owner": {
      "name": "phpcalm",
      "avatar_url": "https://avatars.githubusercontent.com/u/40389646?v=4"
    },
    "telegraph_url": null
  },
  {
    "name": "svar-widgets/react-grid",
    "url": "https://github.com/svar-widgets/react-grid",
    "description": "Fast, feature-rich React datagrid with sorting, filtering, virtual scrolling, and more",
    "stars": 15,
    "forks": 0,
    "language": "JavaScript",
    "topics": [
      "react",
      "react-component",
      "react-data-grid",
      "react-data-table",
      "react-data-table-component",
      "react-datagrid",
      "react-datatable",
      "react-table",
      "react19",
      "reactjs",
      "typescript"
    ],
    "license": "MIT License",
    "created_at": "2025-10-13T15:55:13Z",
    "updated_at": "2025-10-15T14:47:37Z",
    "owner": {
      "name": "svar-widgets",
      "avatar_url": "https://avatars.githubusercontent.com/u/148762960?v=4"
    },
    "telegraph_url": null
  },
  {
    "name": "Dzeksson/powersub-demo-6868",
    "url": "https://github.com/Dzeksson/powersub-demo-6868",
    "description": null,
    "stars": 14,
    "forks": 0,
    "language": "JavaScript",
    "topics": [],
    "license": "No license",
    "created_at": "2025-10-11T18:04:10Z",
    "updated_at": "2025-10-11T18:35:26Z",
    "owner": {
      "name": "Dzeksson",
      "avatar_url": "https://avatars.githubusercontent.com/u/102565922?v=4"
    },
    "telegraph_url": null
  },
  {
    "name": "Dzeksson/powersub-demo-9895",
    "url": "https://github.com/Dzeksson/powersub-demo-9895",
    "description": null,
    "stars": 14,
    "forks": 0,
    "language": "JavaScript",
    "topics": [],
    "license": "No license",
    "created_at": "2025-10-11T18:06:08Z",
    "updated_at": "2025-10-11T18:35:31Z",
    "owner": {
      "name": "Dzeksson",
      "avatar_url": "https://avatars.githubusercontent.com/u/102565922?v=4"
    },
    "telegraph_url": null
  },
  {
    "name": "TheMorpheus407/TheCommunity",
    "url": "https://github.com/TheMorpheus407/TheCommunity",
    "description": "Community Coding Project - USE AT YOUR OWN RISK!",
    "stars": 14,
    "forks": 4,
    "language": "JavaScript",
    "topics": [],
    "license": "The Unlicense",
    "created_at": "2025-10-11T06:33:04Z",
    "updated_at": "2025-10-17T00:35:46Z",
    "owner": {
      "name": "TheMorpheus407",
      "avatar_url": "https://avatars.githubusercontent.com/u/22853222?v=4"
    },
    "telegraph_url": null
  },
  {
    "name": "Dzeksson/powersub-demo-1434",
    "url": "https://github.com/Dzeksson/powersub-demo-1434",
    "description": null,
    "stars": 14,
    "forks": 0,
    "language": "JavaScript",
    "topics": [],
    "license": "No license",
    "created_at": "2025-10-11T18:15:24Z",
    "updated_at": "2025-10-11T18:35:05Z",
    "owner": {
      "name": "Dzeksson",
      "avatar_url": "https://avatars.githubusercontent.com/u/102565922?v=4"
    },
    "telegraph_url": null
  },
  {
    "name": "Dzeksson/powersub-demo-9879",
    "url": "https://github.com/Dzeksson/powersub-demo-9879",
    "description": null,
    "stars": 14,
    "forks": 0,
    "language": "JavaScript",
    "topics": [],
    "license": "No license",
    "created_at": "2025-10-11T17:58:41Z",
    "updated_at": "2025-10-11T18:35:30Z",
    "owner": {
      "name": "Dzeksson",
      "avatar_url": "https://avatars.githubusercontent.com/u/102565922?v=4"
    },
    "telegraph_url": null
  },
  {
    "name": "ritiksahni/zip-over-range",
    "url": "https://github.com/ritiksahni/zip-over-range",
    "description": "Browser-demo for blog titled \"Peeking Inside Gigantic ZIPs with Only Kilobytes\"",
    "stars": 14,
    "forks": 0,
    "language": "JavaScript",
    "topics": [],
    "license": "No license",
    "created_at": "2025-10-12T09:19:32Z",
    "updated_at": "2025-10-16T22:57:30Z",
    "owner": {
      "name": "ritiksahni",
      "avatar_url": "https://avatars.githubusercontent.com/u/58897439?v=4"
    },
    "telegraph_url": null
  }
]