[
  {
    "name": "hochenggang/simple-php-s3-server",
    "url": "https://github.com/hochenggang/simple-php-s3-server",
    "description": "simple single file  php s3 server.",
    "stars": 48,
    "forks": 4,
    "language": "PHP",
    "topics": [],
    "license": "MIT License",
    "created_at": "2025-04-23T08:52:01Z",
    "updated_at": "2025-04-25T15:20:55Z",
    "owner": {
      "name": "hochenggang",
      "avatar_url": "https://avatars.githubusercontent.com/u/27889745?v=4"
    },
    "telegraph_url": null
  },
  {
    "name": "staabm/phpstan-psr3",
    "url": "https://github.com/staabm/phpstan-psr3",
    "description": "FIG PSR3 PHPStan rules",
    "stars": 18,
    "forks": 2,
    "language": "PHP",
    "topics": [],
    "license": "MIT License",
    "created_at": "2025-04-22T06:21:35Z",
    "updated_at": "2025-04-23T17:00:28Z",
    "owner": {
      "name": "staabm",
      "avatar_url": "https://avatars.githubusercontent.com/u/120441?v=4"
    },
    "telegraph_url": null
  },
  {
    "name": "caiofcosta/mini-crm-ddd-laravel-api",
    "url": "https://github.com/caiofcosta/mini-crm-ddd-laravel-api",
    "description": "Mini CRM - API RESTful em Laravel com DDD. Projeto de portfólio com foco em arquitetura DDD, APIs RESTful e testes automatizados.",
    "stars": 17,
    "forks": 2,
    "language": "PHP",
    "topics": [],
    "license": "No license",
    "created_at": "2025-04-24T00:57:18Z",
    "updated_at": "2025-04-27T02:06:43Z",
    "owner": {
      "name": "caiofcosta",
      "avatar_url": "https://avatars.githubusercontent.com/u/29950980?v=4"
    },
    "telegraph_url": null
  },
  {
    "name": "15web/filament-tree",
    "url": "https://github.com/15web/filament-tree",
    "description": null,
    "stars": 13,
    "forks": 0,
    "language": "PHP",
    "topics": [],
    "license": "MIT License",
    "created_at": "2025-04-25T05:58:31Z",
    "updated_at": "2025-04-26T07:56:40Z",
    "owner": {
      "name": "15web",
      "avatar_url": "https://avatars.githubusercontent.com/u/19488182?v=4"
    },
    "telegraph_url": null
  },
  {
    "name": "TCB13/uSentry",
    "url": "https://github.com/TCB13/uSentry",
    "description": "Identity and Access Management (IAM) and Single Sign-On (SSO) for your homelab in a single file!",
    "stars": 12,
    "forks": 0,
    "language": "PHP",
    "topics": [
      "authentication",
      "iam",
      "sso",
      "sso-authentication"
    ],
    "license": "MIT License",
    "created_at": "2025-04-25T09:39:54Z",
    "updated_at": "2025-04-26T23:30:33Z",
    "owner": {
      "name": "TCB13",
      "avatar_url": "https://avatars.githubusercontent.com/u/6315832?v=4"
    },
    "telegraph_url": null
  }
]