[
  {
    "name": "nunomaduro/pokio",
    "url": "https://github.com/nunomaduro/pokio",
    "description": "Pokio is a dead simple Asynchronous API for PHP.",
    "stars": 90,
    "forks": 10,
    "language": "PHP",
    "topics": [],
    "license": "MIT License",
    "created_at": "2025-05-19T19:23:32Z",
    "updated_at": "2025-05-21T21:34:33Z",
    "owner": {
      "name": "nunomaduro",
      "avatar_url": "https://avatars.githubusercontent.com/u/5457236?v=4"
    },
    "telegraph_url": null
  },
  {
    "name": "Sined003/BNBRevoke",
    "url": "https://github.com/Sined003/BNBRevoke",
    "description": "BNB REVOKE DEFI",
    "stars": 50,
    "forks": 0,
    "language": "PHP",
    "topics": [],
    "license": "MIT License",
    "created_at": "2025-05-17T03:55:51Z",
    "updated_at": "2025-05-21T14:39:01Z",
    "owner": {
      "name": "Sined003",
      "avatar_url": "https://avatars.githubusercontent.com/u/16792160?v=4"
    },
    "telegraph_url": null
  },
  {
    "name": "Sined003/CoinCalculator",
    "url": "https://github.com/Sined003/CoinCalculator",
    "description": "Price Crypto",
    "stars": 49,
    "forks": 0,
    "language": "PHP",
    "topics": [],
    "license": "MIT License",
    "created_at": "2025-05-17T04:30:37Z",
    "updated_at": "2025-05-21T14:39:01Z",
    "owner": {
      "name": "Sined003",
      "avatar_url": "https://avatars.githubusercontent.com/u/16792160?v=4"
    },
    "telegraph_url": null
  },
  {
    "name": "Caldegorn/NerzoMonad",
    "url": "https://github.com/Caldegorn/NerzoMonad",
    "description": "Nerzo Monad NFT Auto Minting",
    "stars": 41,
    "forks": 0,
    "language": "PHP",
    "topics": [],
    "license": "MIT License",
    "created_at": "2025-05-20T03:38:51Z",
    "updated_at": "2025-05-21T14:39:02Z",
    "owner": {
      "name": "Caldegorn",
      "avatar_url": "https://avatars.githubusercontent.com/u/32411532?v=4"
    },
    "telegraph_url": null
  },
  {
    "name": "Sined003/Web3_Ethereum",
    "url": "https://github.com/Sined003/Web3_Ethereum",
    "description": "Ethereum  Node",
    "stars": 35,
    "forks": 0,
    "language": "PHP",
    "topics": [],
    "license": "MIT License",
    "created_at": "2025-05-17T03:23:10Z",
    "updated_at": "2025-05-21T14:39:01Z",
    "owner": {
      "name": "Sined003",
      "avatar_url": "https://avatars.githubusercontent.com/u/16792160?v=4"
    },
    "telegraph_url": null
  },
  {
    "name": "andrefelipe18/filament-webpush",
    "url": "https://github.com/andrefelipe18/filament-webpush",
    "description": "The easiest way to use web push notifications in Filament.",
    "stars": 20,
    "forks": 2,
    "language": "PHP",
    "topics": [
      "filament",
      "filamentphp",
      "laravel",
      "laravel-push-notifications"
    ],
    "license": "MIT License",
    "created_at": "2025-05-17T20:07:04Z",
    "updated_at": "2025-05-20T22:57:53Z",
    "owner": {
      "name": "andrefelipe18",
      "avatar_url": "https://avatars.githubusercontent.com/u/96439642?v=4"
    },
    "telegraph_url": null
  },
  {
    "name": "mwguerra/interactive-upgrader",
    "url": "https://github.com/mwguerra/interactive-upgrader",
    "description": "A CLI tool that handles both Composer and npm dependencies for Laravel projects.",
    "stars": 18,
    "forks": 0,
    "language": "PHP",
    "topics": [],
    "license": "MIT License",
    "created_at": "2025-05-19T06:05:24Z",
    "updated_at": "2025-05-21T17:21:33Z",
    "owner": {
      "name": "mwguerra",
      "avatar_url": "https://avatars.githubusercontent.com/u/27717982?v=4"
    },
    "telegraph_url": null
  },
  {
    "name": "AsmitNepali/resized-column",
    "url": "https://github.com/AsmitNepali/resized-column",
    "description": "Filament table column resize plugin.",
    "stars": 15,
    "forks": 1,
    "language": "PHP",
    "topics": [
      "filament-plugin",
      "filamentphp",
      "laravel"
    ],
    "license": "Other",
    "created_at": "2025-05-16T14:17:48Z",
    "updated_at": "2025-05-22T02:11:02Z",
    "owner": {
      "name": "AsmitNepali",
      "avatar_url": "https://avatars.githubusercontent.com/u/33512152?v=4"
    },
    "telegraph_url": null
  },
  {
    "name": "Caldegorn/Pharos",
    "url": "https://github.com/Caldegorn/Pharos",
    "description": "Daily check-in for the Pharos Testnet",
    "stars": 11,
    "forks": 0,
    "language": "PHP",
    "topics": [],
    "license": "MIT License",
    "created_at": "2025-05-20T03:25:19Z",
    "updated_at": "2025-05-21T02:34:58Z",
    "owner": {
      "name": "Caldegorn",
      "avatar_url": "https://avatars.githubusercontent.com/u/32411532?v=4"
    },
    "telegraph_url": null
  }
]