[
  {
    "name": "nunomaduro/essentials",
    "url": "https://github.com/nunomaduro/essentials",
    "description": "Just better defaults for your Laravel projects.",
    "stars": 170,
    "forks": 15,
    "language": "PHP",
    "topics": [],
    "license": "MIT License",
    "created_at": "2025-04-11T20:24:18Z",
    "updated_at": "2025-04-17T01:41:28Z",
    "owner": {
      "name": "nunomaduro",
      "avatar_url": "https://avatars.githubusercontent.com/u/5457236?v=4"
    },
    "telegraph_url": null
  }
]