[
  {
    "name": "hackclub/stardance",
    "url": "https://github.com/hackclub/stardance",
    "description": null,
    "stars": 14,
    "forks": 4,
    "language": "Ruby",
    "topics": [],
    "license": "No license",
    "created_at": "2026-04-11T16:03:46Z",
    "updated_at": "2026-04-17T03:53:03Z",
    "owner": {
      "name": "hackclub",
      "avatar_url": "https://avatars.githubusercontent.com/u/5633654?v=4"
    }
  },
  {
    "name": "palkan/require-profiler",
    "url": "https://github.com/palkan/require-profiler",
    "description": "Profiler for Ruby #require/etc calls",
    "stars": 13,
    "forks": 0,
    "language": "Ruby",
    "topics": [],
    "license": "MIT License",
    "created_at": "2026-04-21T18:06:18Z",
    "updated_at": "2026-04-25T22:10:35Z",
    "owner": {
      "name": "palkan",
      "avatar_url": "https://avatars.githubusercontent.com/u/1516722?v=4"
    }
  },
  {
    "name": "mperham/asynq",
    "url": "https://github.com/mperham/asynq",
    "description": "A lightweight sidekiq client",
    "stars": 11,
    "forks": 0,
    "language": "Ruby",
    "topics": [],
    "license": "MIT License",
    "created_at": "2026-04-27T19:37:01Z",
    "updated_at": "2026-04-28T20:00:22Z",
    "owner": {
      "name": "mperham",
      "avatar_url": "https://avatars.githubusercontent.com/u/2911?v=4"
    }
  },
  {
    "name": "julik/roughrb",
    "url": "https://github.com/julik/roughrb",
    "description": "A port of rough.js to pure Ruby. @radanskoric made me do it 😂",
    "stars": 11,
    "forks": 0,
    "language": "Ruby",
    "topics": [],
    "license": "MIT License",
    "created_at": "2026-04-24T15:49:04Z",
    "updated_at": "2026-04-27T09:56:46Z",
    "owner": {
      "name": "julik",
      "avatar_url": "https://avatars.githubusercontent.com/u/16446?v=4"
    }
  }
]